manipulating_data/__init__.py
manipulating_data/manipulating_data_structures.py
manipulating_data-0.1.1.dist-info/LICENSE.txt
manipulating_data-0.1.1.dist-info/METADATA
manipulating_data-0.1.1.dist-info/WHEEL
manipulating_data-0.1.1.dist-info/top_level.txt
manipulating_data-0.1.1.dist-info/RECORD
