Metadata-Version: 2.1
Name: manipulating-data
Version: 0.1.1
Summary: A package for manipulating Python data structures.
Home-page: UNKNOWN
Author: Krzysztof Chrzan
Author-email: krzysztof.a.chrzan@email.com
License: MIT
Platform: UNKNOWN
License-File: LICENSE.txt
Requires-Dist: pandas
Requires-Dist: numpy
